program_counter/program_counter.v
module program_counter(
    input clk,
    input rst,
    input pc_enable,      // Increment enable
    input pc_load,        // Future branch/jump
    input [7:0] pc_in,
    output reg [7:0] pc
);

always @(posedge clk or posedge rst)
begin
    if (rst)
        pc <= 8'd0;

    else if (pc_load)
        pc <= pc_in;

    else if (pc_enable)
        pc <= pc + 8'd1;

    else
        pc <= pc;      // Hold PC
end

endmodule

program_counter/program_counter_tb.v
module program_counter_tb;
    reg clk;
    reg rst;
    reg pc_enable;      
    reg pc_load;      
    reg  [7:0] pc_in;
    wire [7:0] pc;

    program_counter uut (
        .clk(clk),
        .rst(rst),
        .pc_enable(pc_enable),
        .pc_load(pc_load),
        .pc_in(pc_in),
        .pc(pc)
    );

    initial begin
        clk = 0;
        forever #5 clk = ~clk;
    end

    // Sequence
    initial begin
    $dumpfile("program_counter.vcd");
    $dumpvars(0, program_counter_tb);


        // Initialize
        rst       = 1;
        pc_enable = 0;
        pc_load   = 0;
        pc_in     = 8'd0;

        #12;
        rst = 0;

        // Fetch
        $display("FETCH      : PC = %d", pc);
        #10;

        // Decode
        $display("DECODE     : PC = %d", pc);
        #10;

        // Execute
        $display("EXECUTE    : PC = %d", pc);
        #10;

        // Memory
        $display("MEMORY     : PC = %d", pc);
        #10;

        // Write Back
        pc_enable = 1;
        #10;
        pc_enable = 0;
        $display("WRITE BACK : PC = %d", pc);

        $display("--------------------------");

        // Fetch
        $display("FETCH      : PC = %d", pc);
        #10;

        // Decode
        $display("DECODE     : PC = %d", pc);
        #10;

        // Execute
        $display("EXECUTE    : PC = %d", pc);
        #10;

        // Memory
        $display("MEMORY     : PC = %d", pc);
        #10;

        // Write Back
        pc_enable = 1;
        #10;
        pc_enable = 0;
        $display("WRITE BACK : PC = %d", pc);

        #20;
        $finish;

         $monitor("Time=%0t | PC=%d | Enable=%b",
                 $time, pc, pc_enable);

    end
endmodule

program_counter/program_counter.vcd
$date
	Fri Jul 17 11:49:45 2026
$end
$version
	Icarus Verilog
$end
$timescale
	1s
$end
$scope module program_counter_tb $end
$var wire 8 ! pc [7:0] $end
$var reg 1 " clk $end
$var reg 1 # pc_enable $end
$var reg 8 $ pc_in [7:0] $end
$var reg 1 % pc_load $end
$var reg 1 & rst $end
$scope module uut $end
$var wire 1 " clk $end
$var wire 1 # pc_enable $end
$var wire 8 ' pc_in [7:0] $end
$var wire 1 % pc_load $end
$var wire 1 & rst $end
$var reg 8 ( pc [7:0] $end
$upscope $end
$upscope $end
$enddefinitions $end
#0
$dumpvars
b0 (
b0 '
1&
0%
b0 $
0#
0"
b0 !
$end
#5
1"
#10
0"
#12
0&
#15
1"
#20
0"
#25
1"
#30
0"
#35
1"
#40
0"
#45
1"
#50
0"
#52
1#
#55
b1 !
b1 (
1"
#60
0"
#62
0#
#65
1"
#70
0"
#75
1"
#80
0"
#85
1"
#90
0"
#95
1"
#100
0"
#102
1#
#105
b10 !
b10 (
1"
#110
0"
#112
0#
